pyexcel_gantt/__init__.py
pyexcel_gantt/gantt.py
pyexcel_gantt/utils.py
pyexcel_gantt/templates/embed.html
pyexcel_gantt/templates/full.html
pyexcel_gantt/templates/js/frappe-gantt-0.0.6.min.js
pyexcel_gantt/templates/js/moment-2.18.1.min.js
pyexcel_gantt/templates/js/snap.svg-0.5.1.min.js
pyexcel_gantt-0.0.1.dist-info/DESCRIPTION.rst
pyexcel_gantt-0.0.1.dist-info/METADATA
pyexcel_gantt-0.0.1.dist-info/RECORD
pyexcel_gantt-0.0.1.dist-info/WHEEL
pyexcel_gantt-0.0.1.dist-info/metadata.json
pyexcel_gantt-0.0.1.dist-info/top_level.txt
