Metadata-Version: 1.1
Name: pyexcel-gantt
Version: 0.0.1
Summary: draws gantt chart using frappe-gantt.js for pyexcel data
Home-page: UNKNOWN
Author: C.W.
Author-email: wangc_2011@hotmail.com
License: New BSD
Keywords: excel,python,pyexcel
Platform: UNKNOWN
Classifier: Topic :: Office/Business
Classifier: Topic :: Utilities
Classifier: Topic :: Software Development :: Libraries
Classifier: Programming Language :: Python
Classifier: License :: OSI Approved :: BSD License
Classifier: Intended Audience :: Developers
Classifier: Programming Language :: Python :: 2.6
Classifier: Programming Language :: Python :: 2.7
Classifier: Programming Language :: Python :: 3.3
Classifier: Programming Language :: Python :: 3.4
Classifier: Programming Language :: Python :: 3.5
Classifier: Programming Language :: Python :: 3.6
